[{"__type__":"cc.Prefab","_name":"NameScoreItem","data":{"__id__":1},"asyncLoadAssets":null},{"__type__":"cc.Node","_name":"Node","_children":[{"__id__":2},{"__id__":3},{"__id__":4}],"_prefab":{"__type__":"cc.PrefabInfo","root":{"__id__":1},"asset":{"__id__":0},"fileId":"c5Y7O1zLlNxoYcDtQSrcV1"}},{"__type__":"cc.Node","_name":"text_name","_parent":{"__id__":1},"_components":[{"__type__":"cc.Label","node":{"__id__":2},"_fontSize":20,"_lineHeight":0,"_N$file":{"__uuid__":"e3kKGXTQNEuJvx8NScGeqs"},"_isSystemFontUsed":false,"_N$string":"打阿道夫啊  "}],"_prefab":{"__type__":"cc.PrefabInfo","root":{"__id__":1},"asset":{"__id__":0},"fileId":"35A5z/vn1EsKndMF0b9HSI"},"_color":{"__type__":"cc.Color","r":138,"g":85,"b":51},"_contentSize":{"__type__":"cc.Size","width":110,"height":23},"_position":{"__type__":"cc.Vec2","x":68.001,"y":62.001}},{"__type__":"cc.Node","_name":"atlas_score","_parent":{"__id__":1},"_components":[{"__type__":"cc.StudioComponent","node":{"__id__":3},"_type":2,"_atlasFrame":{"__uuid__":"26vXyMo+JBSJWPQ0L29/pP"},"charWidth":23,"charHeight":37,"string":"0"}],"_prefab":{"__type__":"cc.PrefabInfo","root":{"__id__":1},"asset":{"__id__":0},"fileId":"eexlgdcpZHJ6vxac/58NLc"},"_contentSize":{"__type__":"cc.Size","width":23,"height":37},"_scaleX":0.8,"_scaleY":0.8,"_position":{"__type__":"cc.Vec2","x":68,"y":22.602}},{"__type__":"cc.Node","_name":"img_line_one","_parent":{"__id__":1},"_components":[{"__type__":"cc.Sprite","node":{"__id__":4},"_spriteFrame":{"__uuid__":"384qnKSCVEiqIRTsf/Blhz"},"_sizeMode":2,"_isTrimmedMode":false}],"_prefab":{"__type__":"cc.PrefabInfo","root":{"__id__":1},"asset":{"__id__":0},"fileId":"dcwmwGby1L2pB4BLqnCd4D"},"_contentSize":{"__type__":"cc.Size","width":1,"height":99},"_position":{"__type__":"cc.Vec2","x":140,"y":46.001}}]