[{"__type__":"cc.AnimationClip","_name":"show","_duration":0.9166666666666666,"curveData":{"paths":{"hu08_1":{"props":{"position":[{"frame":0,"value":[0,0]},{"frame":0.25,"value":[0,0]},{"frame":0.3333333333333333,"value":[0,0]},{"frame":0.5833333333333334,"value":[0,0]},{"frame":0.9166666666666666,"value":[0,0]}],"scaleX":[{"frame":0,"value":0.4468},{"frame":0.25,"value":1},{"frame":0.3333333333333333,"value":1},{"frame":0.5833333333333334,"value":0.4468},{"frame":0.9166666666666666,"value":0.4468}],"scaleY":[{"frame":0,"value":0.4468},{"frame":0.25,"value":1},{"frame":0.3333333333333333,"value":1},{"frame":0.5833333333333334,"value":0.4468},{"frame":0.9166666666666666,"value":0.4468}],"rotation":[{"frame":0,"value":0},{"frame":0.25,"value":30},{"frame":0.3333333333333333,"value":40},{"frame":0.5833333333333334,"value":70},{"frame":0.9166666666666666,"value":70}],"opacity":[{"frame":0,"value":0},{"frame":0.25,"value":255},{"frame":0.3333333333333333,"value":255},{"frame":0.5833333333333334,"value":0},{"frame":0.9166666666666666,"value":0}]}}}}},[{"__type__":"cc.Prefab","_name":"xinxin","data":{"__id__":1},"asyncLoadAssets":null},{"__type__":"cc.Node","_name":"Node","_children":[{"__id__":2}],"_components":[{"__type__":"cc.Animation","node":{"__id__":1},"_clips":[{"__uuid__":"b7s/5W21lP0ZnLLRmjFTA1"},{"__uuid__":"43plBaoL9AUqkZQEotMhWP"}]}],"_prefab":{"__type__":"cc.PrefabInfo","root":{"__id__":1},"asset":{"__id__":0},"fileId":"e1ehLwlYJOmak6ogW2kbKM"}},{"__type__":"cc.Node","_name":"hu08_1","_parent":{"__id__":1},"_components":[{"__type__":"cc.Sprite","node":{"__id__":2},"_spriteFrame":{"__uuid__":"9bnkZtnmpPRr0dRuVAX1Jp"},"_sizeMode":2,"_isTrimmedMode":false}],"_prefab":{"__type__":"cc.PrefabInfo","root":{"__id__":1},"asset":{"__id__":0},"fileId":"9d4t+eM2BInbhlzoMrD2LD"},"_opacity":85,"_contentSize":{"__type__":"cc.Size","width":36,"height":35},"_rotationX":10,"_rotationY":10,"_scaleX":0.6312,"_scaleY":0.6312}],{"__type__":"cc.SpriteFrame","content":{"name":"hu08","texture":"75L0X4QH9J76GNwyeDytE1","rect":[1,1,34,33],"offset":[0,0],"originalSize":[36,35]}},{"__type__":"cc.AnimationClip","_name":"xinxin","_duration":0.9166666666666666,"curveData":{"paths":{"hu08_1":{"props":{"position":[{"frame":0,"value":[0,0]},{"frame":0.25,"value":[0,0]},{"frame":0.3333333333333333,"value":[0,0]},{"frame":0.5833333333333334,"value":[0,0]},{"frame":0.9166666666666666,"value":[0,0]}],"scaleX":[{"frame":0,"value":0.4468},{"frame":0.25,"value":1},{"frame":0.3333333333333333,"value":1},{"frame":0.5833333333333334,"value":0.4468},{"frame":0.9166666666666666,"value":0.4468}],"scaleY":[{"frame":0,"value":0.4468},{"frame":0.25,"value":1},{"frame":0.3333333333333333,"value":1},{"frame":0.5833333333333334,"value":0.4468},{"frame":0.9166666666666666,"value":0.4468}],"rotation":[{"frame":0,"value":0},{"frame":0.25,"value":30},{"frame":0.3333333333333333,"value":40},{"frame":0.5833333333333334,"value":70},{"frame":0.9166666666666666,"value":70}],"opacity":[{"frame":0,"value":0},{"frame":0.25,"value":255},{"frame":0.3333333333333333,"value":255},{"frame":0.5833333333333334,"value":0},{"frame":0.9166666666666666,"value":0}]}}}}}]